authortools/__init__.py
authortools/authortools.py
authortools/writing_analysis.py
authortools-0.0.2.dist-info/LICENSE
authortools-0.0.2.dist-info/METADATA
authortools-0.0.2.dist-info/WHEEL
authortools-0.0.2.dist-info/top_level.txt
authortools-0.0.2.dist-info/RECORD
