Metadata-Version: 2.1
Name: authortools
Version: 0.0.2
Summary: A collection of useful functions for writers to analyze text/stories.
Home-page: https://github.com/Codenameaidan/AuthorTools
Author: Codenameaidan
Author-email: codenameaidan@gmail.com
License: MIT
Platform: UNKNOWN
Classifier: License :: OSI Approved :: MIT License
Classifier: Programming Language :: Python :: 3
Classifier: Programming Language :: Python :: 3.7
